LICENSE
motioneye_client/__init__.py
motioneye_client/client.py
motioneye_client/const.py
motioneye_client/py.typed
motioneye_client/utils.py
motioneye_client-0.3.13.dist-info/LICENSE
motioneye_client-0.3.13.dist-info/WHEEL
motioneye_client-0.3.13.dist-info/METADATA
motioneye_client-0.3.13.dist-info/RECORD
