Metadata-Version: 2.1
Name: motioneye-client
Version: 0.3.13
Summary: motionEye client library Python Package
Home-page: https://github.com/dermotduffy/motioneye-client
License: MIT
Keywords: motioneye
Author: Dermot Duffy
Author-email: dermot.duffy@gmail.com
Requires-Python: >=3.8,<4.0
Classifier: Intended Audience :: Developers
Classifier: License :: OSI Approved :: MIT License
Classifier: Operating System :: OS Independent
Classifier: Programming Language :: Python :: 3
Classifier: Programming Language :: Python :: 3.8
Classifier: Programming Language :: Python :: 3.9
Classifier: Topic :: Home Automation
Requires-Dist: aiohttp (>=3.8.3,<4.0.0)
Project-URL: Repository, https://github.com/dermotduffy/motioneye-client
